ipydatawidgets/__init__.py
ipydatawidgets/_frontend.py
ipydatawidgets/_version.py
ipydatawidgets/widgets.py
ipydatawidgets/nbextension/__init__.py
ipydatawidgets/nbextension/static/extension.js
ipydatawidgets/nbextension/static/index.js
ipydatawidgets/nbextension/static/index.js.LICENSE.txt
ipydatawidgets/nbextension/static/index.js.map
ipydatawidgets/ndarray/__init__.py
ipydatawidgets/ndarray/media.py
ipydatawidgets/ndarray/serializers.py
ipydatawidgets/ndarray/traits.py
ipydatawidgets/ndarray/union.py
ipydatawidgets/ndarray/widgets.py
ipydatawidgets/tests/__init__.py
ipydatawidgets/tests/conftest.py
ipydatawidgets/tests/test_nbextension_path.py
ipydatawidgets/tests/test_ndarray_serializers.py
ipydatawidgets/tests/test_ndarray_trait.py
ipydatawidgets/tests/test_union.py
ipydatawidgets/tests/test_widgets.py
ipydatawidgets-4.3.5.data/data/etc/jupyter/nbconfig/notebook.d/jupyter-datawidgets.json
ipydatawidgets-4.3.5.data/data/share/jupyter/lab/extensions/jupyterlab-datawidgets-7.1.2.tgz
ipydatawidgets-4.3.5.data/data/share/jupyter/labextensions/jupyterlab-datawidgets/package.json
ipydatawidgets-4.3.5.data/data/share/jupyter/labextensions/jupyterlab-datawidgets/static/511.22f7942246884696c751.js
ipydatawidgets-4.3.5.data/data/share/jupyter/labextensions/jupyterlab-datawidgets/static/511.22f7942246884696c751.js.LICENSE.txt
ipydatawidgets-4.3.5.data/data/share/jupyter/labextensions/jupyterlab-datawidgets/static/824.9dfde28e806c4451c997.js
ipydatawidgets-4.3.5.data/data/share/jupyter/labextensions/jupyterlab-datawidgets/static/880.b9ae0dbdfd88fcbf13dc.js
ipydatawidgets-4.3.5.data/data/share/jupyter/labextensions/jupyterlab-datawidgets/static/remoteEntry.19c5ede959be6b03cfad.js
ipydatawidgets-4.3.5.data/data/share/jupyter/labextensions/jupyterlab-datawidgets/static/style.js
ipydatawidgets-4.3.5.data/data/share/jupyter/labextensions/jupyterlab-datawidgets/static/third-party-licenses.json
ipydatawidgets-4.3.5.dist-info/LICENSE.txt
ipydatawidgets-4.3.5.dist-info/METADATA
ipydatawidgets-4.3.5.dist-info/WHEEL
ipydatawidgets-4.3.5.dist-info/top_level.txt
ipydatawidgets-4.3.5.dist-info/RECORD
